voltcraft_dlp3306/__init__.py
voltcraft_dlp3306/tcp.py
voltcraft_dlp3306/voltcraft.py
voltcraft_dlp3306/writer.py
voltcraft_dlp3306-0.1.2.dist-info/LICENSE
voltcraft_dlp3306-0.1.2.dist-info/METADATA
voltcraft_dlp3306-0.1.2.dist-info/WHEEL
voltcraft_dlp3306-0.1.2.dist-info/top_level.txt
voltcraft_dlp3306-0.1.2.dist-info/RECORD
