Metadata-Version: 2.1
Name: voltcraft-dlp3306
Version: 0.1.2
Summary: ('A python package to interact with Voltcraft DLP 3306 powersupply',)
Home-page: http://github.com/scaleway/voltcraft-dlp3306
Author: The Scaleway Developers
Author-email: community@scaleway.com
License: Apache 2
Requires-Python: >=3.10.0
License-File: LICENSE
Requires-Dist: scpi==2.5.1
Requires-Dist: dataclasses==0.6
